vendor_argo/__init__.py
vendor_argo/jwt1_7_1/__init__.py
vendor_argo/jwt1_7_1/__main__.py
vendor_argo/jwt1_7_1/algorithms.py
vendor_argo/jwt1_7_1/api_jws.py
vendor_argo/jwt1_7_1/api_jwt.py
vendor_argo/jwt1_7_1/compat.py
vendor_argo/jwt1_7_1/exceptions.py
vendor_argo/jwt1_7_1/help.py
vendor_argo/jwt1_7_1/utils.py
vendor_argo/jwt1_7_1/contrib/__init__.py
vendor_argo/jwt1_7_1/contrib/algorithms/__init__.py
vendor_argo/jwt1_7_1/contrib/algorithms/py_ecdsa.py
vendor_argo/jwt1_7_1/contrib/algorithms/pycrypto.py
vendor_argo/rest_auth/__init__.py
vendor_argo/rest_auth/admin.py
vendor_argo/rest_auth/app_settings.py
vendor_argo/rest_auth/models.py
vendor_argo/rest_auth/serializers.py
vendor_argo/rest_auth/social_serializers.py
vendor_argo/rest_auth/urls.py
vendor_argo/rest_auth/utils.py
vendor_argo/rest_auth/views.py
vendor_argo/rest_auth/locale/cs/LC_MESSAGES/django.po
vendor_argo/rest_auth/locale/de/LC_MESSAGES/django.po
vendor_argo/rest_auth/locale/es/LC_MESSAGES/django.po
vendor_argo/rest_auth/locale/fr/LC_MESSAGES/django.po
vendor_argo/rest_auth/locale/ko/LC_MESSAGES/django.po
vendor_argo/rest_auth/locale/pl/LC_MESSAGES/django.po
vendor_argo/rest_auth/locale/pt_BR/LC_MESSAGES/django.po
vendor_argo/rest_auth/locale/ru/LC_MESSAGES/django.po
vendor_argo/rest_auth/locale/tr/LC_MESSAGES/django.po
vendor_argo/rest_auth/locale/zh_Hans/LC_MESSAGES/django.po
vendor_argo/rest_auth/locale/zh_Hant/LC_MESSAGES/django.po
vendor_argo/rest_auth/registration/__init__.py
vendor_argo/rest_auth/registration/app_settings.py
vendor_argo/rest_auth/registration/serializers.py
vendor_argo/rest_auth/registration/urls.py
vendor_argo/rest_auth/registration/views.py
vendor_argo/rest_framework_jwt/__init__.py
vendor_argo/rest_framework_jwt/authentication.py
vendor_argo/rest_framework_jwt/compat.py
vendor_argo/rest_framework_jwt/models.py
vendor_argo/rest_framework_jwt/serializers.py
vendor_argo/rest_framework_jwt/settings.py
vendor_argo/rest_framework_jwt/test.py
vendor_argo-0.2.0.dist-info/METADATA
vendor_argo-0.2.0.dist-info/WHEEL
vendor_argo-0.2.0.dist-info/licenses/LICENSE
vendor_argo-0.2.0.dist-info/RECORD
