Metadata-Version: 2.3
Name: vendor-argo
Version: 0.2.0
Summary: Add your description here
Author-email: yokotoka <hey@yokotoka.is>
License-File: LICENSE
Requires-Python: >=3.8
Requires-Dist: django>=5.0.4
Requires-Dist: djangorestframework>=3.15.1
